ged4py/__init__.py
ged4py/calendar.py
ged4py/date.py
ged4py/model.py
ged4py/parser.py
ged4py/detail/__init__.py
ged4py/detail/io.py
ged4py/detail/name.py
ged4py-0.4.4.dist-info/AUTHORS.rst
ged4py-0.4.4.dist-info/LICENSE
ged4py-0.4.4.dist-info/METADATA
ged4py-0.4.4.dist-info/WHEEL
ged4py-0.4.4.dist-info/entry_points.txt
ged4py-0.4.4.dist-info/top_level.txt
ged4py-0.4.4.dist-info/zip-safe
ged4py-0.4.4.dist-info/RECORD
