Metadata-Version: 2.1
Name: ged4py
Version: 0.4.4
Summary: GEDCOM tools for Python
Home-page: https://github.com/andy-z/ged4py
Author: Andy Salnikov
Author-email: ged4py@py-dev.com
License: MIT License
Keywords: ged4py
Platform: UNKNOWN
Classifier: Development Status :: 4 - Beta
Classifier: Intended Audience :: Developers
Classifier: License :: OSI Approved :: MIT License
Classifier: Natural Language :: English
Classifier: Programming Language :: Python :: 3
Classifier: Programming Language :: Python :: 3 :: Only
Classifier: Programming Language :: Python :: 3.6
Classifier: Programming Language :: Python :: 3.7
Classifier: Programming Language :: Python :: 3.8
Classifier: Programming Language :: Python :: 3.9
Classifier: Topic :: Sociology :: Genealogy
Requires-Dist: ansel
Requires-Dist: convertdate
